particle45.py
particle45-0.1.0.dist-info/LICENSE
particle45-0.1.0.dist-info/WHEEL
particle45-0.1.0.dist-info/METADATA
particle45-0.1.0.dist-info/RECORD
