Metadata-Version: 2.1
Name: particle45
Version: 0.1.0
Summary: A sample Python package that I want to put onto PyPi.
Author-email: "Matthew J. Lewis" <lightscalar@protonmail.com>
Classifier: License :: OSI Approved :: MIT License
Project-URL: Home, https://www.zeusapi.io
